vdag/__init__.py
vdag-0.dist-info/METADATA
vdag-0.dist-info/WHEEL
vdag-0.dist-info/entry_points.txt
vdag-0.dist-info/RECORD
