Metadata-Version: 2.4
Name: vdag
Version: 0
Summary: Add your description here
Author-email: Shunichiro Nomura <nomura@space.t.u-tokyo.ac.jp>
Requires-Python: >=3.13
